{
  "parent": "minecraft:recipes/root",
  "criteria": {
    "has_the_recipe": {
      "conditions": {
        "recipe": "bit_o_everything:bismuth_ingot_from_bismuth_in_blastfurnace"
      },
      "trigger": "minecraft:recipe_unlocked"
    },
    "hasbismuth": {
      "conditions": {
        "items": [
          {
            "items": [
              "bit_o_everything:bismuth"
            ]
          }
        ]
      },
      "trigger": "minecraft:inventory_changed"
    }
  },
  "requirements": [
    [
      "hasbismuth",
      "has_the_recipe"
    ]
  ],
  "rewards": {
    "recipes": [
      "bit_o_everything:bismuth_ingot_from_bismuth_in_blastfurnace"
    ]
  }
}